<annotation>
	<folder>imgs</folder>
	<filename>PMC2646669-11-09.jpg</filename>
	<path>../imgs/PMC2646669-11-09.jpg</path>
	<source>
		<database>Unknown</database>
	</source>
	<size>
		<width>589</width>
		<height>783</height>
		<depth>3</depth>
	</size>
	<segmented>0</segmented>
	<object>
		<name>body</name>
		<pose>Unspecified</pose>
		<truncated>0</truncated>
		<difficult>0</difficult>
		<bndbox>
			<xmin>40</xmin>
			<ymin>558</ymin>
			<xmax>289</xmax>
			<ymax>740</ymax>
		</bndbox>
	</object>
	<object>
		<name>body</name>
		<pose>Unspecified</pose>
		<truncated>0</truncated>
		<difficult>0</difficult>
		<bndbox>
			<xmin>304</xmin>
			<ymin>40</ymin>
			<xmax>553</xmax>
			<ymax>477</ymax>
		</bndbox>
	</object>
	<object>
		<name>references</name>
		<pose>Unspecified</pose>
		<truncated>0</truncated>
		<difficult>0</difficult>
		<bndbox>
			<xmin>303</xmin>
			<ymin>491</ymin>
			<xmax>553</xmax>
			<ymax>739</ymax>
		</bndbox>
	</object>
	<object>
		<name>figure</name>
		<pose>Unspecified</pose>
		<truncated>0</truncated>
		<difficult>0</difficult>
		<bndbox>
			<xmin>39</xmin>
			<ymin>40</ymin>
			<xmax>286</xmax>
			<ymax>351</ymax>
		</bndbox>
	</object>
	<object>
		<name>figure_caption</name>
		<pose>Unspecified</pose>
		<truncated>0</truncated>
		<difficult>0</difficult>
		<bndbox>
			<xmin>40</xmin>
			<ymin>351</ymin>
			<xmax>286</xmax>
			<ymax>547</ymax>
		</bndbox>
	</object>
</annotation>
