<annotation>
	<folder>imgs</folder>
	<filename>PMC2922725-11-07.jpg</filename>
	<path>../imgs/PMC2922725-11-07.jpg</path>
	<source>
		<database>Unknown</database>
	</source>
	<size>
		<width>595</width>
		<height>842</height>
		<depth>1</depth>
	</size>
	<segmented>0</segmented>
	<object>
		<name>body</name>
		<pose>Unspecified</pose>
		<truncated>0</truncated>
		<difficult>0</difficult>
		<bndbox>
			<xmin>48</xmin>
			<ymin>80</ymin>
			<xmax>550</xmax>
			<ymax>147</ymax>
		</bndbox>
	</object>
	<object>
		<name>body</name>
		<pose>Unspecified</pose>
		<truncated>0</truncated>
		<difficult>0</difficult>
		<bndbox>
			<xmin>44</xmin>
			<ymin>544</ymin>
			<xmax>550</xmax>
			<ymax>761</ymax>
		</bndbox>
	</object>
	<object>
		<name>table_caption</name>
		<pose>Unspecified</pose>
		<truncated>0</truncated>
		<difficult>0</difficult>
		<bndbox>
			<xmin>76</xmin>
			<ymin>158</ymin>
			<xmax>515</xmax>
			<ymax>175</ymax>
		</bndbox>
	</object>
	<object>
		<name>table_caption</name>
		<pose>Unspecified</pose>
		<truncated>0</truncated>
		<difficult>0</difficult>
		<bndbox>
			<xmin>69</xmin>
			<ymin>496</ymin>
			<xmax>527</xmax>
			<ymax>528</ymax>
		</bndbox>
	</object>
	<object>
		<name>table</name>
		<pose>Unspecified</pose>
		<truncated>0</truncated>
		<difficult>0</difficult>
		<bndbox>
			<xmin>136</xmin>
			<ymin>177</ymin>
			<xmax>459</xmax>
			<ymax>493</ymax>
		</bndbox>
	</object>
</annotation>
