<annotation>
	<folder>imgs</folder>
	<filename>PMC3033827-13-06.jpg</filename>
	<path>../imgs/PMC3033827-13-06.jpg</path>
	<source>
		<database>Unknown</database>
	</source>
	<size>
		<width>595</width>
		<height>794</height>
		<depth>3</depth>
	</size>
	<segmented>0</segmented>
	<object>
		<name>figure</name>
		<pose>Unspecified</pose>
		<truncated>0</truncated>
		<difficult>0</difficult>
		<bndbox>
			<xmin>83</xmin>
			<ymin>92</ymin>
			<xmax>514</xmax>
			<ymax>641</ymax>
		</bndbox>
	</object>
	<object>
		<name>figure_caption</name>
		<pose>Unspecified</pose>
		<truncated>0</truncated>
		<difficult>0</difficult>
		<bndbox>
			<xmin>60</xmin>
			<ymin>645</ymin>
			<xmax>535</xmax>
			<ymax>716</ymax>
		</bndbox>
	</object>
</annotation>
