<annotation>
	<folder>imgs</folder>
	<filename>PMC3449288-14-06.jpg</filename>
	<path>../imgs/PMC3449288-14-06.jpg</path>
	<source>
		<database>Unknown</database>
	</source>
	<size>
		<width>595</width>
		<height>842</height>
		<depth>1</depth>
	</size>
	<segmented>0</segmented>
	<object>
		<name>body</name>
		<pose>Unspecified</pose>
		<truncated>0</truncated>
		<difficult>0</difficult>
		<bndbox>
			<xmin>42</xmin>
			<ymin>607</ymin>
			<xmax>295</xmax>
			<ymax>760</ymax>
		</bndbox>
	</object>
	<object>
		<name>body</name>
		<pose>Unspecified</pose>
		<truncated>0</truncated>
		<difficult>0</difficult>
		<bndbox>
			<xmin>300</xmin>
			<ymin>607</ymin>
			<xmax>553</xmax>
			<ymax>760</ymax>
		</bndbox>
	</object>
	<object>
		<name>figure_caption</name>
		<pose>Unspecified</pose>
		<truncated>0</truncated>
		<difficult>0</difficult>
		<bndbox>
			<xmin>49</xmin>
			<ymin>576</ymin>
			<xmax>476</xmax>
			<ymax>592</ymax>
		</bndbox>
	</object>
	<object>
		<name>figure</name>
		<pose>Unspecified</pose>
		<truncated>0</truncated>
		<difficult>0</difficult>
		<bndbox>
			<xmin>48</xmin>
			<ymin>118</ymin>
			<xmax>546</xmax>
			<ymax>569</ymax>
		</bndbox>
	</object>
</annotation>
